{
  "variants": {
    "level=0": { "model": "billtech:block/hydrochloric_acid" },
    "level=1": { "model": "billtech:block/hydrochloric_acid" },
    "level=2": { "model": "billtech:block/hydrochloric_acid" },
    "level=3": { "model": "billtech:block/hydrochloric_acid" },
    "level=4": { "model": "billtech:block/hydrochloric_acid" },
    "level=5": { "model": "billtech:block/hydrochloric_acid" },
    "level=6": { "model": "billtech:block/hydrochloric_acid" },
    "level=7": { "model": "billtech:block/hydrochloric_acid" },
    "level=8": { "model": "billtech:block/hydrochloric_acid" },
    "level=9": { "model": "billtech:block/hydrochloric_acid" },
    "level=10": { "model": "billtech:block/hydrochloric_acid" },
    "level=11": { "model": "billtech:block/hydrochloric_acid" },
    "level=12": { "model": "billtech:block/hydrochloric_acid" },
    "level=13": { "model": "billtech:block/hydrochloric_acid" },
    "level=14": { "model": "billtech:block/hydrochloric_acid" },
    "level=15": { "model": "billtech:block/hydrochloric_acid" }
  }
}
